{"id": 7323, "type": "page", "slug": "chuyen-vien-nghien-cuu-va-phat-trien-hoc-lieu-tieng-anh", "link": "https://ptemagic.com.vn/tuyen-dung/chuyen-vien-nghien-cuu-va-phat-trien-hoc-lieu-tieng-anh/", "title": "CHUYÊN VIÊN NGHIÊN CỨU VÀ PHÁT TRIỂN HỌC LIỆU TIẾNG ANH", "excerpt": "<p>THÔNG TIN CHUNG Chức danh: Chuyên viên R&amp;D mảng học liệu Tiếng Anh Cấp bậc: Nhân viên Bộ phận: Training Quản lý trực tiếp: Training Manager Quản lý gián tiếp: CEO Thời gian làm việc: – Thứ 2 – Thứ 7 hàng tuần (8h/ ngày). – Ngoài giờ: Trong trạng thái Active để kịp thời&#8230;</p>\n", "content": "<ol>\n<li><strong> THÔNG TIN CHUNG</strong></li>\n</ol>\n<div class=\"table-responsive\">\n<table>\n<tbody>\n<tr>\n<td width=\"156\"><strong><em>Chức danh:</em></strong></td>\n<td colspan=\"3\" width=\"468\"><strong>Chuyên viên R&amp;D mảng học liệu Tiếng Anh</strong></td>\n</tr>\n<tr>\n<td width=\"156\"><strong><em>Cấp bậc:</em></strong></td>\n<td colspan=\"3\" width=\"468\">Nhân viên</td>\n</tr>\n<tr>\n<td width=\"156\"><strong><em>Bộ phận:</em></strong></td>\n<td colspan=\"3\" width=\"468\">Training</td>\n</tr>\n<tr>\n<td width=\"156\"><strong><em>Quản lý trực tiếp:</em></strong></td>\n<td width=\"156\">Training Manager</td>\n<td width=\"156\"><strong><em>Quản lý gián tiếp:</em></strong></td>\n<td width=\"156\">CEO</td>\n</tr>\n<tr>\n<td colspan=\"4\" width=\"623\"><strong><em>Thời gian làm việc:</em></strong></p>\n<p>– Thứ 2 – Thứ 7 hàng tuần (8h/ ngày).</p>\n<p>– Ngoài giờ: Trong trạng thái Active để kịp thời xử lý công việc (nếu cần thiết)</p>\n<p>– Tham gia các sự kiện vào cuối tuần khi được phân công (nếu có yêu cầu).</p>\n</td>\n</tr>\n</tbody>\n</table>\n</div>\n<p><strong> </strong></p>\n<ol>\n<li><strong> MỤC TIÊU CÔNG VIỆC: </strong></li>\n</ol>\n<p>– Tạo ra những sản phẩm giảng dạy chất lượng cao, hiệu quả trong việc giúp cho học sinh dễ dàng nắm bắt kiến thức và hứng thú với bài học.</p>\n<p><strong>III. MÔ TẢ CÔNG VIỆC</strong></p>\n<ul>\n<li><strong><em><u>Trách nhiệm:</u></em></strong></li>\n</ul>\n<p>– Nghiên cứu và phát triển các tài liệu &amp; khóa học mới.</p>\n<p>– Kiểm định và đánh giá các khóa học định kì.</p>\n<p>– <strong><em><u>Quyền hạn:</u></em></strong></p>\n<p>– Được tham gia xây dựng kế hoạch, đề xuất các giải pháp, ý tưởng mới nhằm nâng cao chất lượng giáo trình và nội dung giảng dạy.</p>\n<p>– Được đóng góp ý kiến để tạo dựng mội trường làm việc thân thiện và tích cực.</p>\n<p>– Được quyền quyết định, xử lý các công việc đã được quy định trong các quy trình và hướng dẫn công việc đã được giao.</p>\n<p><strong>III. YÊU CẦU</strong></p>\n<p>– Tốt nghiệp đại học trở lên chuyên ngành Sư Phạm, ngôn ngữ Anh,…</p>\n<p>– Có ít nhất 2 năm kinh nghiệm trong lĩnh vực Nghiên cứu và Phát triển ở lĩnh vực giáo dục Tiếng Anh.</p>\n<p>– Hiểu biết về các phương pháp giảng dạy và các xu hướng giảng dạy tiếng Anh mới nhất trên thị trường.</p>\n<p>– Có bằng TESOL và/hoặc bằng Sư Phạm Anh, Ngôn Ngữ Anh là một lợi thế.</p>\n<p>– Trình độ Tiếng Anh: IELTS 7.0+</p>\n<p>– Thành thạo tin học văn phòng, biết cách làm slides.</p>\n<p>– Ưu tiên ứng viên tuổi từ 21~30t.</p>\n<p>– Cần độ RESPONSIVE cao vì công việc xử lí online nhiều.</p>\n<p>– Có khả năng sáng tạo, tư duy nghiên cứu và phân tích thị trường, linh hoạt và có trách nhiệm</p>\n<p>– Cam kết làm việc ít nhất 6 tháng.</p>\n<ol>\n<li><strong> QUYỀN LỢI</strong></li>\n</ol>\n<p>– Lương cơ bản: thỏa thuận trong quá trình phỏng vấn ̣(&gt;12m/tháng).</p>\n<p>– Thử việc: 60 ngày (85% mức lương cơ bản).</p>\n<p>– Môi trường làm việc năng động, trẻ trung, tích cực, được hỗ trợ hết mình.</p>\n<p>– Được đầu tư Đào tạo bằng cấp và chứng chỉ 100%.</p>\n<p>– Lộ trình thăng tiến rõ ràng, phù hợp với khả năng và nhu cầu của từng ứng viên.</p>\n<ol>\n<li><strong> NGHĨA VỤ</strong></li>\n</ol>\n<p>– Bảo mật tuyệt đối các thông tin quan trọng liên quan đến hoạt động trung tâm.</p>\n<p>– Làm việc chủ động và có trách nhiệm.</p>\n<p>– Tuân thủ nội quy công ty.</p>\n<p>– Bảo quản các tài sản, thiết bị được giao.</p>\n<p>CV gửi về: <a href=\"mailto:tuyendung@ptemagic.com.vn\">tuyendung@ptemagic.com.vn</a></p>\n<p>\n\t<section class=\"section\" id=\"section_1869925021\">\n\t\t<div class=\"section-bg fill\" >\n\t\t\t\t\t\t\t\t\t\n\t\t\t\n\n\t\t</div>\n\n\t\t\n\n\t\t<div class=\"section-content relative\">\n\t\t\t</p>\n<p><div class=\"row\"  id=\"row-256749163\"></p>\n<p>\n\t<div id=\"col-229353299\" class=\"col medium-2 small-12 large-2\"  >\n\t\t\t\t<div class=\"col-inner\"  >\n\t\t\t\n\t\t\t</p>\n<p>\t\t</div>\n\t\t\t\t\t</div>\n\n\t<br />\n\n\t<div id=\"col-1405548472\" class=\"col medium-8 small-12 large-8\"  >\n\t\t\t\t<div class=\"col-inner\"  >\n\t\t\t\n\t\t\t</p>\n<p>\t<div id=\"text-2677978117\" class=\"text alert alert-warning wpchuky p-3\">\n\t\t</p>\n<p><div class=\"wpforms-container wpforms-container-full wpforms-instance-inst10\" id=\"wpforms-15316\"><form id=\"wpforms-form-15316-inst10\" class=\"wpforms-validate wpforms-form wpforms-ajax-form\" data-formid=\"15316\" method=\"post\" enctype=\"multipart/form-data\" action=\"/wp-json/wp/v2/pages?per_page=100&#038;page=1&#038;wpforms_form_id=15316\" data-token=\"d352a28c05414eaa31503ddee2d1722b\"><noscript class=\"wpforms-error-noscript\">Vui lòng bật JavaScript trong trình duyệt của bạn để hoàn thành Form này.</noscript><div class=\"wpforms-field-container\"><div id=\"wpforms-15316-field_1-inst10-container\" class=\"wpforms-field wpforms-field-name\" data-field-id=\"1\"><label class=\"wpforms-field-label\" for=\"wpforms-15316-field_1\">Họ và tên <span class=\"wpforms-required-label\">*</span></label><input type=\"text\" id=\"wpforms-15316-field_1-inst10\" class=\"wpforms-field-large wpforms-field-required\" name=\"wpforms[fields][1]\" required></div><div id=\"wpforms-15316-field_2-inst10-container\" class=\"wpforms-field wpforms-field-phone\" data-field-id=\"2\"><label class=\"wpforms-field-label\" for=\"wpforms-15316-field_2\">Số điện thoại <span class=\"wpforms-required-label\">*</span></label><input type=\"tel\" id=\"wpforms-15316-field_2-inst10\" class=\"wpforms-field-large wpforms-field-required wpforms-smart-phone-field\" data-rule-smart-phone-field=\"true\" name=\"wpforms[fields][2]\" required></div><div id=\"wpforms-15316-field_3-inst10-container\" class=\"wpforms-field wpforms-field-email\" data-field-id=\"3\"><label class=\"wpforms-field-label\" for=\"wpforms-15316-field_3\">Email <span class=\"wpforms-required-label\">*</span></label><input type=\"email\" id=\"wpforms-15316-field_3-inst10\" class=\"wpforms-field-large wpforms-field-required\" name=\"wpforms[fields][3]\" required></div><div id=\"wpforms-15316-field_4-inst10-container\" class=\"wpforms-field wpforms-field-text\" data-field-id=\"4\"><label class=\"wpforms-field-label\" for=\"wpforms-15316-field_4\">Trình độ học vấn <span class=\"wpforms-required-label\">*</span></label><input type=\"text\" id=\"wpforms-15316-field_4-inst10\" class=\"wpforms-field-large wpforms-field-required\" name=\"wpforms[fields][4]\" required></div><div id=\"wpforms-15316-field_5-inst10-container\" class=\"wpforms-field wpforms-field-text\" data-field-id=\"5\"><label class=\"wpforms-field-label\" for=\"wpforms-15316-field_5\">Nơi sinh sống hiện tại <span class=\"wpforms-required-label\">*</span></label><input type=\"text\" id=\"wpforms-15316-field_5-inst10\" class=\"wpforms-field-large wpforms-field-required\" name=\"wpforms[fields][5]\" required></div><div id=\"wpforms-15316-field_7-inst10-container\" class=\"wpforms-field wpforms-field-textarea\" data-field-id=\"7\"><label class=\"wpforms-field-label\" for=\"wpforms-15316-field_7\">Mô tả sơ bộ về kinh nghiệm và quá trình làm việc <span class=\"wpforms-required-label\">*</span></label><textarea id=\"wpforms-15316-field_7-inst10\" class=\"wpforms-field-medium wpforms-field-required wpforms-limit-words-enabled\" data-form-id=\"15316\" data-field-id=\"7\" data-text-limit=\"300\" name=\"wpforms[fields][7]\" required></textarea></div><div id=\"wpforms-15316-field_8-inst10-container\" class=\"wpforms-field wpforms-field-file-upload\" data-field-id=\"8\"><label class=\"wpforms-field-label\" for=\"wpforms-15316-field_8\">Upload CV <span class=\"wpforms-required-label\">*</span></label><input type=\"file\" id=\"wpforms-15316-field_8-inst10\" class=\"wpforms-field-required\" data-rule-extension=\"jpg,jpeg,jpe,gif,png,bmp,tiff,tif,webp,avif,ico,heic,heif,heics,heifs,asf,asx,wmv,wmx,wm,avi,divx,mov,qt,mpeg,mpg,mpe,mp4,m4v,ogv,webm,mkv,3gp,3gpp,3g2,3gp2,txt,asc,c,cc,h,srt,csv,tsv,ics,rtx,css,vtt,mp3,m4a,m4b,aac,ra,ram,wav,ogg,oga,flac,mid,midi,wma,wax,mka,rtf,pdf,class,tar,zip,gz,gzip,rar,7z,psd,xcf,doc,pot,pps,ppt,wri,xla,xls,xlt,xlw,mpp,docx,docm,dotx,dotm,xlsx,xlsm,xlsb,xltx,xltm,xlam,pptx,pptm,ppsx,ppsm,potx,potm,ppam,sldx,sldm,onetoc,onetoc2,onepkg,oxps,xps,odt,odp,ods,odg,odc,odb,odf,wp,wpd,key,numbers,pages,json\" data-rule-maxsize=\"26214400\" name=\"wpforms_15316_8\" accept=\".jpg,.jpeg,.jpe,.gif,.png,.bmp,.tiff,.tif,.webp,.avif,.ico,.heic,.heif,.heics,.heifs,.asf,.asx,.wmv,.wmx,.wm,.avi,.divx,.mov,.qt,.mpeg,.mpg,.mpe,.mp4,.m4v,.ogv,.webm,.mkv,.3gp,.3gpp,.3g2,.3gp2,.txt,.asc,.c,.cc,.h,.srt,.csv,.tsv,.ics,.rtx,.css,.vtt,.mp3,.m4a,.m4b,.aac,.ra,.ram,.wav,.ogg,.oga,.flac,.mid,.midi,.wma,.wax,.mka,.rtf,.pdf,.class,.tar,.zip,.gz,.gzip,.rar,.7z,.psd,.xcf,.doc,.pot,.pps,.ppt,.wri,.xla,.xls,.xlt,.xlw,.mpp,.docx,.docm,.dotx,.dotm,.xlsx,.xlsm,.xlsb,.xltx,.xltm,.xlam,.pptx,.pptm,.ppsx,.ppsm,.potx,.potm,.ppam,.sldx,.sldm,.onetoc,.onetoc2,.onepkg,.oxps,.xps,.odt,.odp,.ods,.odg,.odc,.odb,.odf,.wp,.wpd,.key,.numbers,.pages,.json\" required></div></div><div class=\"wpforms-submit-container\"><input type=\"hidden\" name=\"wpforms[id]\" value=\"15316\"><input type=\"hidden\" name=\"wpforms[author]\" value=\"7\"><button type=\"submit\" name=\"wpforms[submit]\" id=\"wpforms-submit-15316\" class=\"wpforms-submit\" data-alt-text=\"Đang gửi...\" data-submit-text=\"Gửi\" aria-live=\"assertive\" value=\"wpforms-submit\">Gửi</button><img decoding=\"async\" src=\"https://ptemagic.com.vn/wp-content/plugins/wpforms/assets/images/submit-spin.svg\" class=\"wpforms-submit-spinner\" style=\"display: none;\" width=\"26\" height=\"26\" alt=\"\"></div></form></div>  <!-- .wpforms-container --><br />\n\t\t\t</div>\n\t</p>\n<p>\t\t</div>\n\t\t\t\t\t</div>\n\n\t</p>\n<p></div></p>\n<p>\t\t</div>\n\n\t\t\n<style>\n#section_1869925021 {\n  padding-top: 30px;\n  padding-bottom: 30px;\n}\n</style>\n\t</section>\n\t</p>\n", "featured_media": 7325, "segments": ["tuyen-dung", "chuyen-vien-nghien-cuu-va-phat-trien-hoc-lieu-tieng-anh"]}