{"id": 4652, "type": "post", "slug": "nam-2022-visa-485-thay-doi", "link": "https://ptemagic.com.vn/nam-2022-visa-485-thay-doi/", "title": "NĂM 2022 – VISA 485 THAY ĐỔI?", "excerpt": "", "content": "<div class=\"x11i5rnm xat24cr x1mh8g0r x1vvkbs xdj266r x126k92a\">\r\n<div dir=\"auto\" style=\"text-align: center;\"> </div>\r\n<div dir=\"auto\"><em>Nếu bạn muốn ở lại Úc sau tốt nghiệp thì visa 485 là một trong những điều bạn cần tìm hiểu qua. Hôm nay hãy cùng PTE Magic điểm qua những lưu ý khi sử dụng loại visa này nhé!</em></div>\r\n<div id=\"ez-toc-container\" class=\"ez-toc-v2_0_55 counter-hierarchy ez-toc-counter ez-toc-grey ez-toc-container-direction\">\n<div class=\"ez-toc-title-container\">\n<p class=\"ez-toc-title \" >Mục Lục </p>\n<span class=\"ez-toc-title-toggle\"><a href=\"#\" class=\"ez-toc-pull-right ez-toc-btn ez-toc-btn-xs ez-toc-btn-default ez-toc-toggle\" aria-label=\"Toggle Table of Content\" role=\"button\"><label for=\"item-6a5f98f479872\" ><span class=\"\"><span style=\"display:none;\">Toggle</span><span class=\"ez-toc-icon-toggle-span\"><svg style=\"fill: #999;color:#999\" xmlns=\"http://www.w3.org/2000/svg\" class=\"list-377408\" width=\"20px\" height=\"20px\" viewBox=\"0 0 24 24\" fill=\"none\"><path d=\"M6 6H4v2h2V6zm14 0H8v2h12V6zM4 11h2v2H4v-2zm16 0H8v2h12v-2zM4 16h2v2H4v-2zm16 0H8v2h12v-2z\" fill=\"currentColor\"></path></svg><svg style=\"fill: #999;color:#999\" class=\"arrow-unsorted-368013\" xmlns=\"http://www.w3.org/2000/svg\" width=\"10px\" height=\"10px\" viewBox=\"0 0 24 24\" version=\"1.2\" baseProfile=\"tiny\"><path d=\"M18.2 9.3l-6.2-6.3-6.2 6.3c-.2.2-.3.4-.3.7s.1.5.3.7c.2.2.4.3.7.3h11c.3 0 .5-.1.7-.3.2-.2.3-.5.3-.7s-.1-.5-.3-.7zM5.8 14.7l6.2 6.3 6.2-6.3c.2-.2.3-.5.3-.7s-.1-.5-.3-.7c-.2-.2-.4-.3-.7-.3h-11c-.3 0-.5.1-.7.3-.2.2-.3.5-.3.7s.1.5.3.7z\"/></svg></span></span></label><input aria-label=\"Toggle\" aria-label=\"item-6a5f98f479872\"  type=\"checkbox\" id=\"item-6a5f98f479872\"></a></span></div>\n<nav><ul class='ez-toc-list ez-toc-list-level-1 eztoc-toggle-hide-by-default' ><li class='ez-toc-page-1 ez-toc-heading-level-2'><a class=\"ez-toc-link ez-toc-heading-1\" href=\"/nam-2022-visa-485-thay-doi/\" title=\"Visa 485 là gì?\">Visa 485 là gì?</a></li><li class='ez-toc-page-1 ez-toc-heading-level-2'><a class=\"ez-toc-link ez-toc-heading-2\" href=\"/nam-2022-visa-485-thay-doi/\" title=\"Những thay đổi Visa 485 trong năm 2022 \">Những thay đổi Visa 485 trong năm 2022 </a></li></ul></nav></div>\n<h2 dir=\"auto\"><span class=\"ez-toc-section\" id=\"Visa_485_la_gi\"></span><strong>Visa 485 là gì?</strong><span class=\"ez-toc-section-end\"></span></h2>\r\n</div>\r\n<div class=\"x11i5rnm xat24cr x1mh8g0r x1vvkbs xtlvy1s x126k92a\">\r\n<div dir=\"auto\" style=\"padding-left: 40px;\"><strong>Visa 485</strong> hay còn gọi là Visa tốt nghiệp tạm thời (Temporary Graduate visa), là dạng thị thực cho phép du học sinh được ở lại Úc làm việc từ 2-4 năm hoặc thậm chí nhiều hơn sau khi tốt nghiệp các chương trình học từ Cử nhân trở lên. Khi được cấp visa này, du học sinh Úc sẽ có thêm thời gian (phụ thuộc vào trình độ hoặc ngành nghề) để tiếp tục làm việc hợp pháp tại Úc.</div>\r\n</div>\r\n<div class=\"x11i5rnm xat24cr x1mh8g0r x1vvkbs xtlvy1s x126k92a\">\r\n<div dir=\"auto\">Từ giữa năm 2022, thị thực này sẽ có giá trị thay thế cho chương trình tốt nghiệp tạm thời COVID-19 (COVID-19 Temporary Graduate). Những đối tượng nào có Temporary Graduate visa đủ điều kiện thay thế cho COVID-19 Temporary Graduate thì sẽ được chính phủ Úc gia hạn thị thực đến ngày 30/09/2022.</div>\r\n<div dir=\"auto\"> </div>\r\n<h2 dir=\"auto\"><span class=\"ez-toc-section\" id=\"Nhung_thay_doi_Visa_485_trong_nam_2022\"></span><strong>Những thay đổi Visa 485 trong năm 2022 </strong><span class=\"ez-toc-section-end\"></span></h2>\r\n</div>\r\n<div class=\"x11i5rnm xat24cr x1mh8g0r x1vvkbs xtlvy1s x126k92a\">\r\n<div dir=\"auto\"> </div>\r\n</div>\r\n<div class=\"x11i5rnm xat24cr x1mh8g0r x1vvkbs xtlvy1s x126k92a\">\r\n<div dir=\"auto\">&#8211; Bỏ yêu cầu đánh giá kỹ năng và xét duyệt tay nghề đối với các hồ sơ visa 485 diện Việc làm được nộp từ ngày 1/7/2022 đến 30/6/2023.</div>\r\n</div>\r\n<div class=\"x11i5rnm xat24cr x1mh8g0r x1vvkbs xtlvy1s x126k92a\">\r\n<div dir=\"auto\">&#8211; Bổ sung thêm diện Thay thế vào danh sách các visa 485 cho du học sinh, dành riêng cho các đối tượng bị ảnh hưởng bởi dịch Covid-19, cụ thể như:</div>\r\n<div dir=\"auto\">+ Đang giữ visa tốt nghiệp tạm thời còn hiệu lực hoặc đã hết hạn từ sau ngày 1/2/2020.</div>\r\n<div dir=\"auto\">+ Ở ngoài nước Úc trong khoảng thời gian từ 1/2/2020 đến 15/12/2021 vì dịch Covid.</div>\r\n</div>\r\n<div class=\"x11i5rnm xat24cr x1mh8g0r x1vvkbs xtlvy1s x126k92a\">\r\n<div dir=\"auto\">&#8211; Thời gian gia hạn của diện visa này tùy thuộc vào diện visa trước đó và thời gian ở lại Úc của du học sinh, cụ thể:</div>\r\n<div dir=\"auto\">+ Nếu trước đó du học sinh tốt nghiệp Thạc Sĩ và được ở lại Úc 2 năm, khi nộp đơn visa 485 diện Thay thế sẽ được tổng cộng 3 năm làm việc tại Úc.</div>\r\n<div dir=\"auto\">+ Tương tự nếu trước đó du học sinh được cấp visa ở lại 18 tháng, thì khi nộp đơn diện Thay thế sẽ được ở lại 2 năm tổng cộng.</div>\r\n</div>\r\n<div class=\"x11i5rnm xat24cr x1mh8g0r x1vvkbs xtlvy1s x126k92a\">\r\n<div dir=\"auto\">Nguồn: <a href=\"https://www.facebook.com/HocluyenthiPTE/photos/a.1825038051103976/3286719331602500/\">Internet</a></div>\r\n<div dir=\"auto\">\r\n<figure id=\"attachment_4653\" aria-describedby=\"caption-attachment-4653\" style=\"width: 300px\" class=\"wp-caption aligncenter\"><img decoding=\"async\" class=\"size-medium wp-image-4653\" src=\"/wp-content/uploads/2022/11/312951279_3286719328269167_5956430181939379953_n-300x252.webp\" alt=\"\" width=\"300\" height=\"252\" srcset=\"/wp-content/uploads/2022/11/312951279_3286719328269167_5956430181939379953_n-300x252.webp 300w, /wp-content/uploads/2022/11/312951279_3286719328269167_5956430181939379953_n.webp 600w\" sizes=\"(max-width: 300px) 100vw, 300px\" /><figcaption id=\"caption-attachment-4653\" class=\"wp-caption-text\">Visa 485 trong năm 2022</figcaption></figure>\r\n</div>\r\n</div>", "featured_media": 4653, "segments": ["nam-2022-visa-485-thay-doi"]}